COCOpy/__init__.py
COCOPLOTS3-0.2.dist-info/METADATA
COCOPLOTS3-0.2.dist-info/WHEEL
COCOPLOTS3-0.2.dist-info/top_level.txt
COCOPLOTS3-0.2.dist-info/RECORD
