Metadata-Version: 2.1
Name: COCOPLOTS3
Version: 0.2
Summary: Python3 version of COCOpy
Home-page: https://github.com/AlexPietrow/COCO
Author: AGM Pietrow
Author-email: alex.pietrow@astro.su.se
License: UNKNOWN
Platform: UNKNOWN
Classifier: Programming Language :: Python :: 3
Classifier: License :: OSI Approved :: MIT License
Classifier: Operating System :: OS Independent
